{
  "$ref": "#/definitions/docs",
  "definitions": {
    "docs": {
      "type": "object",
      "properties": {
        "title": {
          "type": "string"
        },
        "description": {
          "type": "string"
        },
        "draft": {
          "type": "boolean",
          "default": false
        },
        "id": {
          "type": "string"
        },
        "slug": {
          "type": "string"
        },
        "sidebar_label": {
          "type": "string"
        },
        "toplevel": {
          "type": "boolean"
        },
        "redirect": {
          "type": "string"
        },
        "$schema": {
          "type": "string"
        }
      },
      "required": [
        "title"
      ],
      "additionalProperties": false
    }
  },
  "$schema": "http://json-schema.org/draft-07/schema#"
}